convrsn/__init__.py
convrsn/distance.py
convrsn/temperature.py
convrsn-0.1.1.dist-info/METADATA
convrsn-0.1.1.dist-info/WHEEL
convrsn-0.1.1.dist-info/top_level.txt
convrsn-0.1.1.dist-info/RECORD
