Metadata-Version: 2.1
Name: convrsn
Version: 0.1.1
Summary: A conversion package
Author: Stanley M Ndagi
Author-email: ndagis@gmail.com
License: MIT
Keywords: conversion
Classifier: Development Status :: 3 - Alpha
Classifier: Intended Audience :: Developers
Classifier: License :: OSI Approved :: MIT License
Classifier: Programming Language :: Python :: 3
